{
  "name": "Gradebook",
  "fields": [
    {
      "fieldName": "studentCode",
      "fieldType": "String"
    },
    {
      "fieldName": "currentClassCode",
      "fieldType": "String"
    },
    {
      "fieldName": "year",
      "fieldType": "String"
    }
  ],
  "relationships": [],
  "changelogDate": "20210818093815",
  "entityTableName": "student_history",
  "dto": "mapstruct",
  "pagination": "pagination",
  "service": "serviceImpl",
  "jpaMetamodelFiltering": false,
  "fluentMethods": true,
  "readOnly": false,
  "embedded": false,
  "clientRootFolder": "",
  "applications": "*"
}
